rjsmin.py
_rjsmin.cpython-36m-aarch64-linux-gnu.so
rjsmin-1.2.5.dist-info/top_level.txt
rjsmin-1.2.5.dist-info/RECORD
rjsmin-1.2.5.dist-info/LICENSE
rjsmin-1.2.5.dist-info/METADATA
rjsmin-1.2.5.dist-info/WHEEL
